{
  "version": "1.0",
  "generado_en": "2026-06-26T11:05:39.468503+00:00",
  "version_id": "20260626T110524Z",
  "dataset_hash": "0836a797b848e99ec598028a1b2ea53be606bf70577c729cede16567c5be7d93",
  "estado": "modelo_calibrado_entrenado",
  "sklearn_disponible": true,
  "numpy_disponible": true,
  "joblib_disponible": true,
  "modelo_calibrado": true,
  "artefacto_modelo": {
    "guardado": true,
    "calibrado": true,
    "rutas": [
      "data/modelo_predictivo/modelo_entrenado.joblib",
      "data/modelo_predictivo/modelo_calibrado.joblib",
      "data/modelo_predictivo/versiones/20260626T110524Z/modelo_entrenado.joblib",
      "data/modelo_predictivo/versiones/20260626T110524Z/modelo_calibrado.joblib"
    ]
  },
  "muestras": 971,
  "muestras_por_competicion": {
    "liga_extranjera": 562,
    "primera_division": 193,
    "segunda_division": 165,
    "mundial_2026": 51
  },
  "baseline_elo_poisson": {
    "muestras": 971,
    "accuracy_top1": 46.447,
    "brier_score": 0.634098,
    "log_loss": 1.051536,
    "calibration_curve": [
      {
        "bin": "0.3-0.4",
        "muestras": 272,
        "confianza_media": 37.724,
        "acierto_top1": 42.647
      },
      {
        "bin": "0.4-0.5",
        "muestras": 534,
        "confianza_media": 43.811,
        "acierto_top1": 44.007
      },
      {
        "bin": "0.5-0.6",
        "muestras": 144,
        "confianza_media": 54.197,
        "acierto_top1": 55.556
      },
      {
        "bin": "0.6-0.7",
        "muestras": 21,
        "confianza_media": 63.668,
        "acierto_top1": 95.238
      },
      {
        "bin": "0.9-1.0",
        "muestras": 971,
        "confianza_media": 44.075,
        "acierto_top1": 46.447
      }
    ],
    "por_competicion": {
      "liga_extranjera": {
        "muestras": 562,
        "accuracy_top1": 46.263,
        "brier_score": 0.636143,
        "log_loss": 1.053184
      },
      "mundial_2026": {
        "muestras": 51,
        "accuracy_top1": 47.059,
        "brier_score": 0.653152,
        "log_loss": 1.080134
      },
      "primera_division": {
        "muestras": 193,
        "accuracy_top1": 53.886,
        "brier_score": 0.596342,
        "log_loss": 0.999458
      },
      "segunda_division": {
        "muestras": 165,
        "accuracy_top1": 38.182,
        "brier_score": 0.665403,
        "log_loss": 1.097998
      }
    },
    "por_signo_real": {
      "1": {
        "muestras": 440,
        "accuracy_top1": 82.045,
        "brier_score": 0.501598,
        "log_loss": 0.860532
      },
      "2": {
        "muestras": 294,
        "accuracy_top1": 30.272,
        "brier_score": 0.677547,
        "log_loss": 1.106363
      },
      "X": {
        "muestras": 237,
        "accuracy_top1": 0.422,
        "brier_score": 0.826189,
        "log_loss": 1.338127
      }
    }
  },
  "modelo_entrenable_in_sample": {
    "muestras": 971,
    "accuracy_top1": 45.726,
    "brier_score": 0.627368,
    "log_loss": 1.040136,
    "calibration_curve": [
      {
        "bin": "0.3-0.4",
        "muestras": 34,
        "confianza_media": 39.109,
        "acierto_top1": 32.353
      },
      {
        "bin": "0.4-0.5",
        "muestras": 818,
        "confianza_media": 45.133,
        "acierto_top1": 43.032
      },
      {
        "bin": "0.5-0.6",
        "muestras": 118,
        "confianza_media": 52.604,
        "acierto_top1": 67.797
      },
      {
        "bin": "0.6-0.7",
        "muestras": 1,
        "confianza_media": 61.862,
        "acierto_top1": 100.0
      },
      {
        "bin": "0.9-1.0",
        "muestras": 971,
        "confianza_media": 45.847,
        "acierto_top1": 45.726
      }
    ],
    "por_competicion": {
      "liga_extranjera": {
        "muestras": 562,
        "accuracy_top1": 44.84,
        "brier_score": 0.629841,
        "log_loss": 1.043248
      },
      "mundial_2026": {
        "muestras": 51,
        "accuracy_top1": 39.216,
        "brier_score": 0.643103,
        "log_loss": 1.061463
      },
      "primera_division": {
        "muestras": 193,
        "accuracy_top1": 52.332,
        "brier_score": 0.598298,
        "log_loss": 1.000888
      },
      "segunda_division": {
        "muestras": 165,
        "accuracy_top1": 43.03,
        "brier_score": 0.648087,
        "log_loss": 1.068853
      }
    },
    "por_signo_real": {
      "1": {
        "muestras": 440,
        "accuracy_top1": 97.273,
        "brier_score": 0.434663,
        "log_loss": 0.768977
      },
      "2": {
        "muestras": 294,
        "accuracy_top1": 5.442,
        "brier_score": 0.725617,
        "log_loss": 1.157935
      },
      "X": {
        "muestras": 237,
        "accuracy_top1": 0.0,
        "brier_score": 0.863255,
        "log_loss": 1.397424
      }
    }
  },
  "backtesting_rolling": {
    "estado": "ok",
    "muestras_backtesting": 929,
    "metricas": {
      "muestras": 929,
      "accuracy_top1": 44.995,
      "brier_score": 0.639696,
      "log_loss": 1.059668,
      "calibration_curve": [
        {
          "bin": "0.3-0.4",
          "muestras": 46,
          "confianza_media": 38.704,
          "acierto_top1": 43.478
        },
        {
          "bin": "0.4-0.5",
          "muestras": 700,
          "confianza_media": 45.774,
          "acierto_top1": 42.429
        },
        {
          "bin": "0.5-0.6",
          "muestras": 181,
          "confianza_media": 52.48,
          "acierto_top1": 54.696
        },
        {
          "bin": "0.6-0.7",
          "muestras": 2,
          "confianza_media": 62.463,
          "acierto_top1": 100.0
        },
        {
          "bin": "0.9-1.0",
          "muestras": 929,
          "confianza_media": 46.767,
          "acierto_top1": 44.995
        }
      ],
      "por_competicion": {
        "liga_extranjera": {
          "muestras": 545,
          "accuracy_top1": 44.404,
          "brier_score": 0.640362,
          "log_loss": 1.059768
        },
        "mundial_2026": {
          "muestras": 51,
          "accuracy_top1": 39.216,
          "brier_score": 0.670507,
          "log_loss": 1.094561
        },
        "primera_division": {
          "muestras": 177,
          "accuracy_top1": 51.412,
          "brier_score": 0.608118,
          "log_loss": 1.017817
        },
        "segunda_division": {
          "muestras": 156,
          "accuracy_top1": 41.667,
          "brier_score": 0.663125,
          "log_loss": 1.095392
        }
      },
      "por_signo_real": {
        "1": {
          "muestras": 424,
          "accuracy_top1": 95.519,
          "brier_score": 0.432245,
          "log_loss": 0.765856
        },
        "2": {
          "muestras": 280,
          "accuracy_top1": 4.286,
          "brier_score": 0.774283,
          "log_loss": 1.237452
        },
        "X": {
          "muestras": 225,
          "accuracy_top1": 0.444,
          "brier_score": 0.863141,
          "log_loss": 1.392097
        }
      }
    },
    "ultimas_predicciones": [
      {
        "jornada": 36,
        "num": 7,
        "competicion": "liga_extranjera",
        "y": "X",
        "probs": {
          "1": 0.3602094,
          "X": 0.20746979,
          "2": 0.43232082
        },
        "top": "2",
        "acierto_top1": false
      },
      {
        "jornada": 36,
        "num": 8,
        "competicion": "liga_extranjera",
        "y": "2",
        "probs": {
          "1": 0.46012395,
          "X": 0.24665884,
          "2": 0.29321721
        },
        "top": "1",
        "acierto_top1": false
      },
      {
        "jornada": 36,
        "num": 9,
        "competicion": "liga_extranjera",
        "y": "1",
        "probs": {
          "1": 0.49554935,
          "X": 0.2489859,
          "2": 0.25546475
        },
        "top": "1",
        "acierto_top1": true
      },
      {
        "jornada": 36,
        "num": 10,
        "competicion": "liga_extranjera",
        "y": "2",
        "probs": {
          "1": 0.39245683,
          "X": 0.19169365,
          "2": 0.41584952
        },
        "top": "2",
        "acierto_top1": true
      },
      {
        "jornada": 36,
        "num": 11,
        "competicion": "liga_extranjera",
        "y": "2",
        "probs": {
          "1": 0.4874744,
          "X": 0.23010899,
          "2": 0.2824166
        },
        "top": "1",
        "acierto_top1": false
      },
      {
        "jornada": 36,
        "num": 12,
        "competicion": "liga_extranjera",
        "y": "1",
        "probs": {
          "1": 0.49015458,
          "X": 0.25098059,
          "2": 0.25886483
        },
        "top": "1",
        "acierto_top1": true
      },
      {
        "jornada": 36,
        "num": 13,
        "competicion": "liga_extranjera",
        "y": "1",
        "probs": {
          "1": 0.44661407,
          "X": 0.22766474,
          "2": 0.32572119
        },
        "top": "1",
        "acierto_top1": true
      },
      {
        "jornada": 36,
        "num": 14,
        "competicion": "liga_extranjera",
        "y": "1",
        "probs": {
          "1": 0.5004108,
          "X": 0.24519207,
          "2": 0.25439713
        },
        "top": "1",
        "acierto_top1": true
      },
      {
        "jornada": 58,
        "num": 1,
        "competicion": "liga_extranjera",
        "y": "1",
        "probs": {
          "1": 0.51138131,
          "X": 0.26196497,
          "2": 0.22665372
        },
        "top": "1",
        "acierto_top1": true
      },
      {
        "jornada": 58,
        "num": 2,
        "competicion": "liga_extranjera",
        "y": "1",
        "probs": {
          "1": 0.48378064,
          "X": 0.21079941,
          "2": 0.30541995
        },
        "top": "1",
        "acierto_top1": true
      },
      {
        "jornada": 58,
        "num": 3,
        "competicion": "primera_division",
        "y": "1",
        "probs": {
          "1": 0.46785263,
          "X": 0.18654791,
          "2": 0.34559946
        },
        "top": "1",
        "acierto_top1": true
      },
      {
        "jornada": 58,
        "num": 4,
        "competicion": "primera_division",
        "y": "X",
        "probs": {
          "1": 0.46672356,
          "X": 0.17682934,
          "2": 0.3564471
        },
        "top": "1",
        "acierto_top1": false
      },
      {
        "jornada": 58,
        "num": 5,
        "competicion": "primera_division",
        "y": "X",
        "probs": {
          "1": 0.37214203,
          "X": 0.18939064,
          "2": 0.43846733
        },
        "top": "2",
        "acierto_top1": false
      },
      {
        "jornada": 58,
        "num": 6,
        "competicion": "liga_extranjera",
        "y": "1",
        "probs": {
          "1": 0.46066182,
          "X": 0.26417695,
          "2": 0.27516123
        },
        "top": "1",
        "acierto_top1": true
      },
      {
        "jornada": 58,
        "num": 7,
        "competicion": "liga_extranjera",
        "y": "1",
        "probs": {
          "1": 0.37151359,
          "X": 0.21955502,
          "2": 0.40893139
        },
        "top": "2",
        "acierto_top1": false
      },
      {
        "jornada": 58,
        "num": 8,
        "competicion": "liga_extranjera",
        "y": "1",
        "probs": {
          "1": 0.46503436,
          "X": 0.231012,
          "2": 0.30395364
        },
        "top": "1",
        "acierto_top1": true
      },
      {
        "jornada": 58,
        "num": 9,
        "competicion": "primera_division",
        "y": "2",
        "probs": {
          "1": 0.50415006,
          "X": 0.23290362,
          "2": 0.26294632
        },
        "top": "1",
        "acierto_top1": false
      },
      {
        "jornada": 58,
        "num": 10,
        "competicion": "liga_extranjera",
        "y": "1",
        "probs": {
          "1": 0.45057121,
          "X": 0.19446523,
          "2": 0.35496356
        },
        "top": "1",
        "acierto_top1": true
      },
      {
        "jornada": 58,
        "num": 11,
        "competicion": "liga_extranjera",
        "y": "2",
        "probs": {
          "1": 0.45300905,
          "X": 0.24420023,
          "2": 0.30279072
        },
        "top": "1",
        "acierto_top1": false
      },
      {
        "jornada": 58,
        "num": 12,
        "competicion": "liga_extranjera",
        "y": "X",
        "probs": {
          "1": 0.46250919,
          "X": 0.24815159,
          "2": 0.28933922
        },
        "top": "1",
        "acierto_top1": false
      },
      {
        "jornada": 58,
        "num": 13,
        "competicion": "liga_extranjera",
        "y": "2",
        "probs": {
          "1": 0.47741639,
          "X": 0.25071486,
          "2": 0.27186875
        },
        "top": "1",
        "acierto_top1": false
      },
      {
        "jornada": 58,
        "num": 14,
        "competicion": "liga_extranjera",
        "y": "X",
        "probs": {
          "1": 0.462757,
          "X": 0.24785853,
          "2": 0.28938447
        },
        "top": "1",
        "acierto_top1": false
      },
      {
        "jornada": 15,
        "num": 1,
        "competicion": "liga_extranjera",
        "y": "1",
        "probs": {
          "1": 0.53032936,
          "X": 0.22115085,
          "2": 0.2485198
        },
        "top": "1",
        "acierto_top1": true
      },
      {
        "jornada": 15,
        "num": 2,
        "competicion": "liga_extranjera",
        "y": "1",
        "probs": {
          "1": 0.39410184,
          "X": 0.21364341,
          "2": 0.39225475
        },
        "top": "1",
        "acierto_top1": true
      },
      {
        "jornada": 15,
        "num": 3,
        "competicion": "liga_extranjera",
        "y": "2",
        "probs": {
          "1": 0.41465038,
          "X": 0.24103624,
          "2": 0.34431338
        },
        "top": "1",
        "acierto_top1": false
      },
      {
        "jornada": 15,
        "num": 4,
        "competicion": "liga_extranjera",
        "y": "2",
        "probs": {
          "1": 0.4570556,
          "X": 0.23677958,
          "2": 0.30616482
        },
        "top": "1",
        "acierto_top1": false
      },
      {
        "jornada": 15,
        "num": 5,
        "competicion": "liga_extranjera",
        "y": "1",
        "probs": {
          "1": 0.5226549,
          "X": 0.23714223,
          "2": 0.24020288
        },
        "top": "1",
        "acierto_top1": true
      },
      {
        "jornada": 15,
        "num": 6,
        "competicion": "liga_extranjera",
        "y": "1",
        "probs": {
          "1": 0.45822499,
          "X": 0.23061147,
          "2": 0.31116353
        },
        "top": "1",
        "acierto_top1": true
      },
      {
        "jornada": 15,
        "num": 7,
        "competicion": "liga_extranjera",
        "y": "2",
        "probs": {
          "1": 0.45646688,
          "X": 0.23067499,
          "2": 0.31285813
        },
        "top": "1",
        "acierto_top1": false
      },
      {
        "jornada": 15,
        "num": 8,
        "competicion": "liga_extranjera",
        "y": "2",
        "probs": {
          "1": 0.4534234,
          "X": 0.27366357,
          "2": 0.27291304
        },
        "top": "1",
        "acierto_top1": false
      },
      {
        "jornada": 15,
        "num": 9,
        "competicion": "liga_extranjera",
        "y": "1",
        "probs": {
          "1": 0.45009772,
          "X": 0.23559972,
          "2": 0.31430255
        },
        "top": "1",
        "acierto_top1": true
      },
      {
        "jornada": 15,
        "num": 10,
        "competicion": "liga_extranjera",
        "y": "1",
        "probs": {
          "1": 0.42874479,
          "X": 0.26239036,
          "2": 0.30886485
        },
        "top": "1",
        "acierto_top1": true
      },
      {
        "jornada": 15,
        "num": 11,
        "competicion": "liga_extranjera",
        "y": "2",
        "probs": {
          "1": 0.43610742,
          "X": 0.19607397,
          "2": 0.36781862
        },
        "top": "1",
        "acierto_top1": false
      },
      {
        "jornada": 15,
        "num": 12,
        "competicion": "liga_extranjera",
        "y": "1",
        "probs": {
          "1": 0.55728265,
          "X": 0.27661889,
          "2": 0.16609846
        },
        "top": "1",
        "acierto_top1": true
      },
      {
        "jornada": 15,
        "num": 13,
        "competicion": "liga_extranjera",
        "y": "X",
        "probs": {
          "1": 0.45929087,
          "X": 0.23058133,
          "2": 0.3101278
        },
        "top": "1",
        "acierto_top1": false
      },
      {
        "jornada": 15,
        "num": 14,
        "competicion": "liga_extranjera",
        "y": "1",
        "probs": {
          "1": 0.47520746,
          "X": 0.21917082,
          "2": 0.30562171
        },
        "top": "1",
        "acierto_top1": true
      },
      {
        "jornada": 8,
        "num": 1,
        "competicion": "primera_division",
        "y": "X",
        "probs": {
          "1": 0.51108711,
          "X": 0.22124071,
          "2": 0.26767218
        },
        "top": "1",
        "acierto_top1": false
      },
      {
        "jornada": 8,
        "num": 2,
        "competicion": "primera_division",
        "y": "X",
        "probs": {
          "1": 0.46633812,
          "X": 0.22750431,
          "2": 0.30615758
        },
        "top": "1",
        "acierto_top1": false
      },
      {
        "jornada": 8,
        "num": 3,
        "competicion": "primera_division",
        "y": "2",
        "probs": {
          "1": 0.45807212,
          "X": 0.2203028,
          "2": 0.32162508
        },
        "top": "1",
        "acierto_top1": false
      },
      {
        "jornada": 8,
        "num": 4,
        "competicion": "primera_division",
        "y": "2",
        "probs": {
          "1": 0.41583583,
          "X": 0.24905625,
          "2": 0.33510792
        },
        "top": "1",
        "acierto_top1": false
      },
      {
        "jornada": 8,
        "num": 5,
        "competicion": "liga_extranjera",
        "y": "X",
        "probs": {
          "1": 0.45000775,
          "X": 0.21402468,
          "2": 0.33596758
        },
        "top": "1",
        "acierto_top1": false
      },
      {
        "jornada": 8,
        "num": 6,
        "competicion": "primera_division",
        "y": "2",
        "probs": {
          "1": 0.31590587,
          "X": 0.22633529,
          "2": 0.45775883
        },
        "top": "2",
        "acierto_top1": true
      },
      {
        "jornada": 8,
        "num": 7,
        "competicion": "liga_extranjera",
        "y": "X",
        "probs": {
          "1": 0.43219589,
          "X": 0.23361708,
          "2": 0.33418704
        },
        "top": "1",
        "acierto_top1": false
      },
      {
        "jornada": 8,
        "num": 8,
        "competicion": "primera_division",
        "y": "1",
        "probs": {
          "1": 0.49503921,
          "X": 0.25582482,
          "2": 0.24913597
        },
        "top": "1",
        "acierto_top1": true
      },
      {
        "jornada": 8,
        "num": 9,
        "competicion": "liga_extranjera",
        "y": "X",
        "probs": {
          "1": 0.45758319,
          "X": 0.27512581,
          "2": 0.267291
        },
        "top": "1",
        "acierto_top1": false
      },
      {
        "jornada": 8,
        "num": 10,
        "competicion": "liga_extranjera",
        "y": "X",
        "probs": {
          "1": 0.48548073,
          "X": 0.24477513,
          "2": 0.26974414
        },
        "top": "1",
        "acierto_top1": false
      },
      {
        "jornada": 8,
        "num": 11,
        "competicion": "liga_extranjera",
        "y": "2",
        "probs": {
          "1": 0.44699759,
          "X": 0.24007781,
          "2": 0.3129246
        },
        "top": "1",
        "acierto_top1": false
      },
      {
        "jornada": 8,
        "num": 12,
        "competicion": "liga_extranjera",
        "y": "1",
        "probs": {
          "1": 0.55576633,
          "X": 0.27151455,
          "2": 0.17271912
        },
        "top": "1",
        "acierto_top1": true
      },
      {
        "jornada": 8,
        "num": 13,
        "competicion": "liga_extranjera",
        "y": "2",
        "probs": {
          "1": 0.43677902,
          "X": 0.23539932,
          "2": 0.32782165
        },
        "top": "1",
        "acierto_top1": false
      },
      {
        "jornada": 8,
        "num": 14,
        "competicion": "liga_extranjera",
        "y": "1",
        "probs": {
          "1": 0.43843776,
          "X": 0.26093276,
          "2": 0.30062947
        },
        "top": "1",
        "acierto_top1": true
      },
      {
        "jornada": 23,
        "num": 1,
        "competicion": "liga_extranjera",
        "y": "2",
        "probs": {
          "1": 0.46593871,
          "X": 0.25201079,
          "2": 0.28205051
        },
        "top": "1",
        "acierto_top1": false
      },
      {
        "jornada": 23,
        "num": 2,
        "competicion": "liga_extranjera",
        "y": "1",
        "probs": {
          "1": 0.50515763,
          "X": 0.23019489,
          "2": 0.26464748
        },
        "top": "1",
        "acierto_top1": true
      },
      {
        "jornada": 23,
        "num": 3,
        "competicion": "liga_extranjera",
        "y": "1",
        "probs": {
          "1": 0.34003892,
          "X": 0.2436076,
          "2": 0.41635348
        },
        "top": "2",
        "acierto_top1": false
      },
      {
        "jornada": 23,
        "num": 4,
        "competicion": "liga_extranjera",
        "y": "2",
        "probs": {
          "1": 0.49691257,
          "X": 0.25646541,
          "2": 0.24662202
        },
        "top": "1",
        "acierto_top1": false
      },
      {
        "jornada": 23,
        "num": 5,
        "competicion": "liga_extranjera",
        "y": "1",
        "probs": {
          "1": 0.42031107,
          "X": 0.25522835,
          "2": 0.32446058
        },
        "top": "1",
        "acierto_top1": true
      },
      {
        "jornada": 23,
        "num": 6,
        "competicion": "liga_extranjera",
        "y": "X",
        "probs": {
          "1": 0.45840196,
          "X": 0.24879862,
          "2": 0.29279942
        },
        "top": "1",
        "acierto_top1": false
      },
      {
        "jornada": 23,
        "num": 7,
        "competicion": "liga_extranjera",
        "y": "1",
        "probs": {
          "1": 0.39352339,
          "X": 0.2321317,
          "2": 0.37434491
        },
        "top": "1",
        "acierto_top1": true
      },
      {
        "jornada": 23,
        "num": 8,
        "competicion": "liga_extranjera",
        "y": "2",
        "probs": {
          "1": 0.47212168,
          "X": 0.23211629,
          "2": 0.29576203
        },
        "top": "1",
        "acierto_top1": false
      },
      {
        "jornada": 23,
        "num": 9,
        "competicion": "liga_extranjera",
        "y": "2",
        "probs": {
          "1": 0.49161308,
          "X": 0.25388445,
          "2": 0.25450248
        },
        "top": "1",
        "acierto_top1": false
      },
      {
        "jornada": 23,
        "num": 10,
        "competicion": "liga_extranjera",
        "y": "2",
        "probs": {
          "1": 0.41434149,
          "X": 0.25461001,
          "2": 0.33104849
        },
        "top": "1",
        "acierto_top1": false
      },
      {
        "jornada": 23,
        "num": 11,
        "competicion": "liga_extranjera",
        "y": "1",
        "probs": {
          "1": 0.52828842,
          "X": 0.24458619,
          "2": 0.22712539
        },
        "top": "1",
        "acierto_top1": true
      },
      {
        "jornada": 23,
        "num": 12,
        "competicion": "liga_extranjera",
        "y": "1",
        "probs": {
          "1": 0.46627549,
          "X": 0.25401496,
          "2": 0.27970956
        },
        "top": "1",
        "acierto_top1": true
      },
      {
        "jornada": 23,
        "num": 13,
        "competicion": "liga_extranjera",
        "y": "1",
        "probs": {
          "1": 0.43034709,
          "X": 0.24617956,
          "2": 0.32347335
        },
        "top": "1",
        "acierto_top1": true
      },
      {
        "jornada": 23,
        "num": 14,
        "competicion": "liga_extranjera",
        "y": "1",
        "probs": {
          "1": 0.48966946,
          "X": 0.27177371,
          "2": 0.23855683
        },
        "top": "1",
        "acierto_top1": true
      },
      {
        "jornada": 38,
        "num": 1,
        "competicion": "liga_extranjera",
        "y": "2",
        "probs": {
          "1": 0.49379898,
          "X": 0.26592868,
          "2": 0.24027234
        },
        "top": "1",
        "acierto_top1": false
      },
      {
        "jornada": 38,
        "num": 2,
        "competicion": "liga_extranjera",
        "y": "2",
        "probs": {
          "1": 0.44009006,
          "X": 0.23282525,
          "2": 0.32708469
        },
        "top": "1",
        "acierto_top1": false
      },
      {
        "jornada": 38,
        "num": 3,
        "competicion": "liga_extranjera",
        "y": "2",
        "probs": {
          "1": 0.47656536,
          "X": 0.25464344,
          "2": 0.2687912
        },
        "top": "1",
        "acierto_top1": false
      },
      {
        "jornada": 38,
        "num": 4,
        "competicion": "liga_extranjera",
        "y": "1",
        "probs": {
          "1": 0.49506491,
          "X": 0.23615556,
          "2": 0.26877953
        },
        "top": "1",
        "acierto_top1": true
      },
      {
        "jornada": 38,
        "num": 5,
        "competicion": "liga_extranjera",
        "y": "1",
        "probs": {
          "1": 0.46953355,
          "X": 0.23177302,
          "2": 0.29869343
        },
        "top": "1",
        "acierto_top1": true
      },
      {
        "jornada": 38,
        "num": 6,
        "competicion": "liga_extranjera",
        "y": "2",
        "probs": {
          "1": 0.50007446,
          "X": 0.24495894,
          "2": 0.2549666
        },
        "top": "1",
        "acierto_top1": false
      },
      {
        "jornada": 38,
        "num": 7,
        "competicion": "liga_extranjera",
        "y": "1",
        "probs": {
          "1": 0.50879108,
          "X": 0.25546561,
          "2": 0.23574331
        },
        "top": "1",
        "acierto_top1": true
      },
      {
        "jornada": 38,
        "num": 8,
        "competicion": "liga_extranjera",
        "y": "1",
        "probs": {
          "1": 0.50132058,
          "X": 0.25071355,
          "2": 0.24796587
        },
        "top": "1",
        "acierto_top1": true
      },
      {
        "jornada": 38,
        "num": 9,
        "competicion": "liga_extranjera",
        "y": "X",
        "probs": {
          "1": 0.42527761,
          "X": 0.23764969,
          "2": 0.33707269
        },
        "top": "1",
        "acierto_top1": false
      },
      {
        "jornada": 38,
        "num": 10,
        "competicion": "liga_extranjera",
        "y": "2",
        "probs": {
          "1": 0.45658722,
          "X": 0.25257454,
          "2": 0.29083825
        },
        "top": "1",
        "acierto_top1": false
      },
      {
        "jornada": 38,
        "num": 11,
        "competicion": "liga_extranjera",
        "y": "2",
        "probs": {
          "1": 0.43581446,
          "X": 0.23396264,
          "2": 0.3302229
        },
        "top": "1",
        "acierto_top1": false
      },
      {
        "jornada": 38,
        "num": 12,
        "competicion": "liga_extranjera",
        "y": "X",
        "probs": {
          "1": 0.50911635,
          "X": 0.24100356,
          "2": 0.24988009
        },
        "top": "1",
        "acierto_top1": false
      },
      {
        "jornada": 38,
        "num": 13,
        "competicion": "liga_extranjera",
        "y": "X",
        "probs": {
          "1": 0.45255014,
          "X": 0.23884621,
          "2": 0.30860365
        },
        "top": "1",
        "acierto_top1": false
      },
      {
        "jornada": 38,
        "num": 14,
        "competicion": "liga_extranjera",
        "y": "1",
        "probs": {
          "1": 0.48538436,
          "X": 0.25337768,
          "2": 0.26123796
        },
        "top": "1",
        "acierto_top1": true
      },
      {
        "jornada": 25,
        "num": 1,
        "competicion": "liga_extranjera",
        "y": "1",
        "probs": {
          "1": 0.43549069,
          "X": 0.21889934,
          "2": 0.34560997
        },
        "top": "1",
        "acierto_top1": true
      },
      {
        "jornada": 25,
        "num": 2,
        "competicion": "liga_extranjera",
        "y": "2",
        "probs": {
          "1": 0.45126392,
          "X": 0.24455335,
          "2": 0.30418273
        },
        "top": "1",
        "acierto_top1": false
      },
      {
        "jornada": 25,
        "num": 3,
        "competicion": "segunda_division",
        "y": "1",
        "probs": {
          "1": 0.42570775,
          "X": 0.23255078,
          "2": 0.34174147
        },
        "top": "1",
        "acierto_top1": true
      },
      {
        "jornada": 25,
        "num": 4,
        "competicion": "liga_extranjera",
        "y": "2",
        "probs": {
          "1": 0.47632999,
          "X": 0.23344633,
          "2": 0.29022368
        },
        "top": "1",
        "acierto_top1": false
      },
      {
        "jornada": 25,
        "num": 5,
        "competicion": "liga_extranjera",
        "y": "1",
        "probs": {
          "1": 0.44119178,
          "X": 0.23576283,
          "2": 0.32304539
        },
        "top": "1",
        "acierto_top1": true
      },
      {
        "jornada": 25,
        "num": 6,
        "competicion": "liga_extranjera",
        "y": "1",
        "probs": {
          "1": 0.4237628,
          "X": 0.25305634,
          "2": 0.32318086
        },
        "top": "1",
        "acierto_top1": true
      },
      {
        "jornada": 25,
        "num": 7,
        "competicion": "liga_extranjera",
        "y": "2",
        "probs": {
          "1": 0.46206715,
          "X": 0.23427112,
          "2": 0.30366172
        },
        "top": "1",
        "acierto_top1": false
      },
      {
        "jornada": 25,
        "num": 8,
        "competicion": "segunda_division",
        "y": "2",
        "probs": {
          "1": 0.4439838,
          "X": 0.23747618,
          "2": 0.31854003
        },
        "top": "1",
        "acierto_top1": false
      },
      {
        "jornada": 25,
        "num": 9,
        "competicion": "liga_extranjera",
        "y": "2",
        "probs": {
          "1": 0.46178129,
          "X": 0.24281662,
          "2": 0.29540208
        },
        "top": "1",
        "acierto_top1": false
      },
      {
        "jornada": 25,
        "num": 10,
        "competicion": "liga_extranjera",
        "y": "2",
        "probs": {
          "1": 0.44813799,
          "X": 0.23200154,
          "2": 0.31986047
        },
        "top": "1",
        "acierto_top1": false
      },
      {
        "jornada": 25,
        "num": 11,
        "competicion": "liga_extranjera",
        "y": "2",
        "probs": {
          "1": 0.44751639,
          "X": 0.22949978,
          "2": 0.32298382
        },
        "top": "1",
        "acierto_top1": false
      },
      {
        "jornada": 25,
        "num": 12,
        "competicion": "liga_extranjera",
        "y": "2",
        "probs": {
          "1": 0.4228859,
          "X": 0.23542645,
          "2": 0.34168766
        },
        "top": "1",
        "acierto_top1": false
      },
      {
        "jornada": 25,
        "num": 13,
        "competicion": "liga_extranjera",
        "y": "2",
        "probs": {
          "1": 0.42985276,
          "X": 0.24006383,
          "2": 0.33008341
        },
        "top": "1",
        "acierto_top1": false
      },
      {
        "jornada": 25,
        "num": 14,
        "competicion": "primera_division",
        "y": "2",
        "probs": {
          "1": 0.42644526,
          "X": 0.23113665,
          "2": 0.34241809
        },
        "top": "1",
        "acierto_top1": false
      },
      {
        "jornada": 18,
        "num": 1,
        "competicion": "liga_extranjera",
        "y": "1",
        "probs": {
          "1": 0.5424964,
          "X": 0.23528098,
          "2": 0.22222262
        },
        "top": "1",
        "acierto_top1": true
      },
      {
        "jornada": 18,
        "num": 2,
        "competicion": "liga_extranjera",
        "y": "2",
        "probs": {
          "1": 0.50280694,
          "X": 0.24159766,
          "2": 0.2555954
        },
        "top": "1",
        "acierto_top1": false
      },
      {
        "jornada": 18,
        "num": 3,
        "competicion": "liga_extranjera",
        "y": "X",
        "probs": {
          "1": 0.47982787,
          "X": 0.2357788,
          "2": 0.28439333
        },
        "top": "1",
        "acierto_top1": false
      },
      {
        "jornada": 18,
        "num": 4,
        "competicion": "liga_extranjera",
        "y": "X",
        "probs": {
          "1": 0.43203513,
          "X": 0.24449805,
          "2": 0.32346683
        },
        "top": "1",
        "acierto_top1": false
      },
      {
        "jornada": 18,
        "num": 5,
        "competicion": "liga_extranjera",
        "y": "2",
        "probs": {
          "1": 0.47315641,
          "X": 0.23142383,
          "2": 0.29541976
        },
        "top": "1",
        "acierto_top1": false
      },
      {
        "jornada": 18,
        "num": 6,
        "competicion": "liga_extranjera",
        "y": "1",
        "probs": {
          "1": 0.467035,
          "X": 0.2450422,
          "2": 0.2879228
        },
        "top": "1",
        "acierto_top1": true
      },
      {
        "jornada": 18,
        "num": 7,
        "competicion": "liga_extranjera",
        "y": "1",
        "probs": {
          "1": 0.45199324,
          "X": 0.20143243,
          "2": 0.34657432
        },
        "top": "1",
        "acierto_top1": true
      },
      {
        "jornada": 18,
        "num": 8,
        "competicion": "liga_extranjera",
        "y": "X",
        "probs": {
          "1": 0.43327054,
          "X": 0.2414682,
          "2": 0.32526126
        },
        "top": "1",
        "acierto_top1": false
      },
      {
        "jornada": 18,
        "num": 9,
        "competicion": "liga_extranjera",
        "y": "2",
        "probs": {
          "1": 0.47018239,
          "X": 0.22486111,
          "2": 0.30495649
        },
        "top": "1",
        "acierto_top1": false
      },
      {
        "jornada": 18,
        "num": 10,
        "competicion": "liga_extranjera",
        "y": "2",
        "probs": {
          "1": 0.41827912,
          "X": 0.23283895,
          "2": 0.34888193
        },
        "top": "1",
        "acierto_top1": false
      },
      {
        "jornada": 18,
        "num": 11,
        "competicion": "liga_extranjera",
        "y": "X",
        "probs": {
          "1": 0.39094112,
          "X": 0.21446648,
          "2": 0.3945924
        },
        "top": "2",
        "acierto_top1": false
      },
      {
        "jornada": 18,
        "num": 12,
        "competicion": "liga_extranjera",
        "y": "1",
        "probs": {
          "1": 0.43634529,
          "X": 0.23685836,
          "2": 0.32679635
        },
        "top": "1",
        "acierto_top1": true
      },
      {
        "jornada": 18,
        "num": 13,
        "competicion": "liga_extranjera",
        "y": "2",
        "probs": {
          "1": 0.48714425,
          "X": 0.2310432,
          "2": 0.28181256
        },
        "top": "1",
        "acierto_top1": false
      },
      {
        "jornada": 18,
        "num": 14,
        "competicion": "liga_extranjera",
        "y": "1",
        "probs": {
          "1": 0.49715036,
          "X": 0.2346981,
          "2": 0.26815154
        },
        "top": "1",
        "acierto_top1": true
      },
      {
        "jornada": 54,
        "num": 1,
        "competicion": "liga_extranjera",
        "y": "2",
        "probs": {
          "1": 0.47953242,
          "X": 0.27478424,
          "2": 0.24568334
        },
        "top": "1",
        "acierto_top1": false
      },
      {
        "jornada": 54,
        "num": 2,
        "competicion": "liga_extranjera",
        "y": "2",
        "probs": {
          "1": 0.37533415,
          "X": 0.25367995,
          "2": 0.3709859
        },
        "top": "1",
        "acierto_top1": false
      },
      {
        "jornada": 54,
        "num": 3,
        "competicion": "liga_extranjera",
        "y": "1",
        "probs": {
          "1": 0.48262634,
          "X": 0.25779758,
          "2": 0.25957608
        },
        "top": "1",
        "acierto_top1": true
      },
      {
        "jornada": 54,
        "num": 4,
        "competicion": "liga_extranjera",
        "y": "X",
        "probs": {
          "1": 0.4699506,
          "X": 0.24320572,
          "2": 0.28684368
        },
        "top": "1",
        "acierto_top1": false
      },
      {
        "jornada": 54,
        "num": 5,
        "competicion": "liga_extranjera",
        "y": "2",
        "probs": {
          "1": 0.39540576,
          "X": 0.21213713,
          "2": 0.39245711
        },
        "top": "1",
        "acierto_top1": false
      },
      {
        "jornada": 54,
        "num": 6,
        "competicion": "liga_extranjera",
        "y": "1",
        "probs": {
          "1": 0.51788003,
          "X": 0.24074662,
          "2": 0.24137335
        },
        "top": "1",
        "acierto_top1": true
      },
      {
        "jornada": 54,
        "num": 7,
        "competicion": "liga_extranjera",
        "y": "X",
        "probs": {
          "1": 0.44627843,
          "X": 0.24064927,
          "2": 0.3130723
        },
        "top": "1",
        "acierto_top1": false
      },
      {
        "jornada": 54,
        "num": 8,
        "competicion": "liga_extranjera",
        "y": "1",
        "probs": {
          "1": 0.42941104,
          "X": 0.22174298,
          "2": 0.34884598
        },
        "top": "1",
        "acierto_top1": true
      },
      {
        "jornada": 54,
        "num": 9,
        "competicion": "liga_extranjera",
        "y": "1",
        "probs": {
          "1": 0.4403242,
          "X": 0.23204095,
          "2": 0.32763486
        },
        "top": "1",
        "acierto_top1": true
      },
      {
        "jornada": 54,
        "num": 10,
        "competicion": "liga_extranjera",
        "y": "1",
        "probs": {
          "1": 0.35997195,
          "X": 0.20618319,
          "2": 0.43384486
        },
        "top": "2",
        "acierto_top1": false
      },
      {
        "jornada": 54,
        "num": 11,
        "competicion": "liga_extranjera",
        "y": "1",
        "probs": {
          "1": 0.46702789,
          "X": 0.22937816,
          "2": 0.30359394
        },
        "top": "1",
        "acierto_top1": true
      },
      {
        "jornada": 54,
        "num": 12,
        "competicion": "liga_extranjera",
        "y": "2",
        "probs": {
          "1": 0.44963607,
          "X": 0.24233314,
          "2": 0.3080308
        },
        "top": "1",
        "acierto_top1": false
      },
      {
        "jornada": 54,
        "num": 13,
        "competicion": "liga_extranjera",
        "y": "2",
        "probs": {
          "1": 0.44982528,
          "X": 0.24230573,
          "2": 0.30786899
        },
        "top": "1",
        "acierto_top1": false
      },
      {
        "jornada": 54,
        "num": 14,
        "competicion": "liga_extranjera",
        "y": "2",
        "probs": {
          "1": 0.42100075,
          "X": 0.22794221,
          "2": 0.35105704
        },
        "top": "1",
        "acierto_top1": false
      }
    ]
  },
  "nota": "El backtesting rolling es la metrica principal; in_sample solo diagnostica ajuste interno."
}
